{
	"Zones": [
		{
			"LocalIndex": 0, //Starting
			"SubSeed": 0,
			"BulkheadDCScanSeed": 0,
			"SubComplex": "Refinery",
			"CoverageMinMax": {
				"x": 10.0,
				"y": 20.0
			},
			"BuildFromLocalIndex": 0,
			"StartPosition": "From_Start",
			"StartPosition_IndexWeight": 0.0,
			"StartExpansion": "Towards_Right",
			"ZoneExpansion": "Directional_Right",
			"LightSettings": 56,
			"AltitudeData": {
				"AllowedZoneAltitude": "OnlyLow",
				"ChanceToChange": 1.0
			},
			"EventsOnEnter": [],
			"ProgressionPuzzleToEnter": {
				"PuzzleType": 0,
				"CustomText": "<color=red>://ERROR: Door in emergency lockdown, unable to operate.</color>",
				"PlacementCount": 1,
				"ZonePlacementData": []
			},
			"ChainedPuzzleToEnter": 36,
			"SecurityGateToEnter": 0,
			"ActiveEnemyWave": {
				"HasActiveEnemyWave": false,
				"EnemyGroupInfrontOfDoor": 0,
				"EnemyGroupInArea": 0,
				"EnemyGroupsInArea": 0
			},
			"EnemySpawningInZone": [
				{
					"GroupType": 0,
					"Difficulty": 0,
					"Distribution": 2,
					"DistributionValue": 0.5
				}
			],
			"HSUClustersInZone": 0,
			"CorpseClustersInZone": 0,
			"ResourceContainerClustersInZone": 0,
			"GeneratorClustersInZone": 0,
			"CorpsesInZone": 0,
			"HSUsInZone": 0,
			"DeconUnitsInZone": 0,
			"AllowSmallPickupsAllocation": true,
			"AllowResourceContainerAllocation": true,
			"ForceBigPickupsAllocation": false,
			"ConsumableDistributionInZone": 9,
			"BigPickupDistributionInZone": 0,
			"TerminalPlacements": [
				{
					"PlacementWeights": {
						"Start": 0.0,
						"Middle": 0.0,
						"End": 0.0
					}
				}
			],
			"ForbidTerminalsInZone": false,
			"PowerGeneratorPlacements": [],
			"DisinfectionStationPlacements": [],
			"HealthMulti": 0.0,
			"HealthPlacement": {
				"Start": 0.0,
				"Middle": 0.0,
				"End": 0.0
			},
			"WeaponAmmoMulti": 0.0,
			"WeaponAmmoPlacement": {
				"Start": 0.0,
				"Middle": 0.0,
				"End": 0.0
			},
			"ToolAmmoMulti": 0.0,
			"ToolAmmoPlacement": {
				"Start": 0.0,
				"Middle": 0.0,
				"End": 0.0
			},
			"DisinfectionMulti": 0.0,
			"DisinfectionPlacement": {
				"Start": 0.0,
				"Middle": 0.0,
				"End": 0.0
			}
		},
		{
			"LocalIndex": 1, //P1, BULK KEY
			"SubSeed": 0,
			"BulkheadDCScanSeed": 0,
			"SubComplex": "Refinery",
			"CoverageMinMax": {
				"x": 1.0,
				"y": 5.0
			},
			"BuildFromLocalIndex": 0,
			"StartPosition": "From_Furthest",
			"StartPosition_IndexWeight": 0.0,
			"StartExpansion": "Towards_Right",
			"ZoneExpansion": "Directional_Right",
			"LightSettings": 56,
			"AltitudeData": {
				"AllowedZoneAltitude": "OnlyLow",
				"ChanceToChange": 1.0
			},
			"EventsOnEnter": [],
			"ProgressionPuzzleToEnter": {
				"PuzzleType": 3,
				"CustomText": "<color=red>Class [://E__R#999] Alarm Detected!</color>",
				"PlacementCount": 1,
				"ZonePlacementData": []
			},
			"ChainedPuzzleToEnter": 0,
			"SecurityGateToEnter": 0,
			"ActiveEnemyWave": {
				"HasActiveEnemyWave": false,
				"EnemyGroupInfrontOfDoor": 0,
				"EnemyGroupInArea": 0,
				"EnemyGroupsInArea": 0
			},
			"EnemySpawningInZone": [
				{
					"GroupType": 0,
					"Difficulty": 0,
					"Distribution": 2,
					"DistributionValue": 0.1
				},
				{
					"GroupType": 3,
					"Difficulty": 0,
					"Distribution": 1,
					"DistributionValue": 1.0
				}
			],
			"HSUClustersInZone": 0,
			"CorpseClustersInZone": 0,
			"ResourceContainerClustersInZone": 0,
			"GeneratorClustersInZone": 0,
			"CorpsesInZone": 0,
			"HSUsInZone": 0,
			"DeconUnitsInZone": 0,
			"AllowSmallPickupsAllocation": true,
			"AllowResourceContainerAllocation": true,
			"ForceBigPickupsAllocation": false,
			"ConsumableDistributionInZone": 9,
			"BigPickupDistributionInZone": 0,
			"TerminalPlacements": [
				{
					"PlacementWeights": {
						"Start": 0.0,
						"Middle": 0.0,
						"End": 0.0
					}
				}
			],
			"ForbidTerminalsInZone": false,
			"PowerGeneratorPlacements": [],
			"DisinfectionStationPlacements": [],
			"HealthMulti": 0.0,
			"HealthPlacement": {
				"Start": 0.0,
				"Middle": 0.0,
				"End": 0.0
			},
			"WeaponAmmoMulti": 0.0,
			"WeaponAmmoPlacement": {
				"Start": 0.0,
				"Middle": 0.0,
				"End": 0.0
			},
			"ToolAmmoMulti": 0.0,
			"ToolAmmoPlacement": {
				"Start": 0.0,
				"Middle": 0.0,
				"End": 0.0
			},
			"DisinfectionMulti": 0.0,
			"DisinfectionPlacement": {
				"Start": 0.0,
				"Middle": 0.0,
				"End": 0.0
			}
		}
	],
	"name": "A4_L2",
	"internalEnabled": true,
	"persistentID": "Layout_A4_L2",
	"datablock": "LevelLayout"
}